visaionlibrary/__init__.py
visaionlibrary/datasets/__init__.py
visaionlibrary/datasets/cls_dataset.py
visaionlibrary/datasets/det_dataset.py
visaionlibrary/datasets/ins_dataset.py
visaionlibrary/datasets/seg_dataset.py
visaionlibrary/datasets/samplers/__init__.py
visaionlibrary/datasets/samplers/batch_sampler.py
visaionlibrary/datasets/samplers/sampler.py
visaionlibrary/datasets/transforms/__init__.py
visaionlibrary/datasets/transforms/formatting.py
visaionlibrary/datasets/transforms/loading.py
visaionlibrary/datasets/transforms/process.py
visaionlibrary/datasets/transforms/region_sampler.py
visaionlibrary/datasets/utils/__init__.py
visaionlibrary/datasets/utils/sample_status.py
visaionlibrary/datasets/utils/str2mask.py
visaionlibrary/engine/__init__.py
visaionlibrary/engine/hooks/__init__.py
visaionlibrary/engine/hooks/pipeline_switch_hook.py
visaionlibrary/engine/hooks/yolov5_param_scheduler_hook.py
visaionlibrary/evaluation/__init__.py
visaionlibrary/evaluation/metrics/__init__.py
visaionlibrary/evaluation/metrics/cls_metric.py
visaionlibrary/evaluation/metrics/coco_metric.py
visaionlibrary/evaluation/metrics/det_metrics.py
visaionlibrary/evaluation/metrics/seg_metric.py
visaionlibrary/models/__init__.py
visaionlibrary/models/backbones/__init__.py
visaionlibrary/models/backbones/csp_darknet.py
visaionlibrary/models/data_preprocessor/__init__.py
visaionlibrary/models/data_preprocessor/det_data_preprocessor.py
visaionlibrary/models/data_preprocessor/seg_data_preprocessor.py
visaionlibrary/models/dense_heads/yolo11_head.py
visaionlibrary/models/ins/RTMDetInsSepBNHead.py
visaionlibrary/models/ins/__init__.py
visaionlibrary/models/ins/yolo11InsHead.py
visaionlibrary/models/layers/yolo_bricks.py
visaionlibrary/models/necks/yolo11_pafpn.py
visaionlibrary/models/seg/__init__.py
visaionlibrary/models/seg/decode_head.py
visaionlibrary/models/seg/encoder_decoder.py
visaionlibrary/models/seg/hyh_unet_head.py
visaionlibrary/models/seg/regnet.py
visaionlibrary-0.6.22.dist-info/licenses/LICENSE
visaionlibrary-0.6.22.dist-info/METADATA
visaionlibrary-0.6.22.dist-info/WHEEL
visaionlibrary-0.6.22.dist-info/top_level.txt
visaionlibrary-0.6.22.dist-info/RECORD
